avantis_trader_sdk/__init__.py
avantis_trader_sdk/client.py
avantis_trader_sdk/config.py
avantis_trader_sdk/types.py
avantis_trader_sdk/utils.py
avantis_trader_sdk/abis/AggregatorV3Interface.json
avantis_trader_sdk/abis/Sanctions.json
avantis_trader_sdk/abis/__init__.py
avantis_trader_sdk/abis/ABDK.t.sol/ABDKTest.json
avantis_trader_sdk/abis/AbstractPyth.sol/AbstractPyth.json
avantis_trader_sdk/abis/AccessControl.sol/AccessControl.json
avantis_trader_sdk/abis/Address.sol/Address.json
avantis_trader_sdk/abis/Address.sol/Addresses.json
avantis_trader_sdk/abis/AddressUpgradeable.sol/AddressUpgradeable.json
avantis_trader_sdk/abis/AggregatorInterface.sol/AggregatorInterface.json
avantis_trader_sdk/abis/AggregatorV2V3Interface.sol/AggregatorV2V3Interface.json
avantis_trader_sdk/abis/AggregatorV3Interface.sol/AggregatorV3Interface.json
avantis_trader_sdk/abis/BackupOracle.t.sol/BackupOracle.json
avantis_trader_sdk/abis/Base.sol/CommonBase.json
avantis_trader_sdk/abis/Base.sol/ScriptBase.json
avantis_trader_sdk/abis/Base.sol/TestBase.json
avantis_trader_sdk/abis/Base.t.sol/Base.json
avantis_trader_sdk/abis/Constants.sol/Constants.json
avantis_trader_sdk/abis/Context.sol/Context.json
avantis_trader_sdk/abis/ContextUpgradeable.sol/ContextUpgradeable.json
avantis_trader_sdk/abis/Counters.sol/Counters.json
avantis_trader_sdk/abis/ERC165.sol/ERC165.json
avantis_trader_sdk/abis/ERC165Upgradeable.sol/ERC165Upgradeable.json
avantis_trader_sdk/abis/ERC1967/ERC1967Proxy.sol/ERC1967Proxy.json
avantis_trader_sdk/abis/ERC1967/ERC1967Upgrade.sol/ERC1967Upgrade.json
avantis_trader_sdk/abis/ERC1967Proxy.sol/ERC1967Proxy.json
avantis_trader_sdk/abis/ERC1967Upgrade.sol/ERC1967Upgrade.json
avantis_trader_sdk/abis/ERC20.sol/ERC20.json
avantis_trader_sdk/abis/ERC20Upgradeable.sol/ERC20Upgradeable.json
avantis_trader_sdk/abis/ERC4626Upgradeable.sol/ERC4626Upgradeable.json
avantis_trader_sdk/abis/ERC721Upgradeable.sol/ERC721Upgradeable.json
avantis_trader_sdk/abis/Execute.sol/Execute.json
avantis_trader_sdk-0.8.13.dist-info/METADATA
avantis_trader_sdk-0.8.13.dist-info/WHEEL
avantis_trader_sdk-0.8.13.dist-info/top_level.txt
avantis_trader_sdk-0.8.13.dist-info/RECORD
