Metadata-Version: 2.4
Name: avantis_trader_sdk
Version: 0.8.13
Summary: SDK for interacting with Avantis trading contracts.
Home-page: https://avantisfi.com/
Author: Avantis Labs
Author-email: yug@avantisfi.com
License: MIT
Keywords: trading sdk blockchain ethereum web3 avantis
Classifier: Programming Language :: Python :: 3
Classifier: License :: OSI Approved :: MIT License
Classifier: Operating System :: OS Independent
Requires-Python: >=3.6
Requires-Dist: web3<7,>=6.15.1
Requires-Dist: pydantic<3,>=2.8.2
Requires-Dist: websockets<14,>=12.0
Requires-Dist: boto3<2,>=1.35.44
Requires-Dist: eth_account<0.14,>=0.10.0
Requires-Dist: toolz<1,>=0.12.1
Requires-Dist: eth_utils<5,>=2.1.0
Requires-Dist: pyasn1<1,>=0.6.1
Dynamic: author
Dynamic: author-email
Dynamic: classifier
Dynamic: description
Dynamic: description-content-type
Dynamic: home-page
Dynamic: keywords
Dynamic: license
Dynamic: requires-dist
Dynamic: requires-python
Dynamic: summary
